
[{
    "_id" : ObjectId("51d743e44e7eecde4762cb9c"),
    "personal" : {
        "fname" : "Jon",
        "lname" : "Mittelbronn",
        "emailAddress" : "jmittelbronn@sapient.com",
        "address" : "435 Maker Sail Circle",
        "city" : "Atlanta",
        "zip" : "30022",
        "ssn" : "XXX-XX-XXXX",
        "gender" : "M",
        "maritalStatus" : "Married",
        "phone" : {
            "home" : "555-555-5555",
            "work" : "666-666-6666",
            "cell" : "777-777-7777"
        },
        "dob" : {
            "month" : 12,
            "date" : 18,
            "year" : 1979
        },
        "userGuid" : "12434mjhicdfi4k34u39iu"
    },
    "system" : {
        "password" : "m3l155412",
        "username" : "jmit"
    },
    "insurance" : {
        "mainInsured" : {
            "relationTo" : "self",
            "fname" : "Jon",
            "lname" : "Mittelbronn",
            "emailAddress" : "jmittelbronn@sapient.com",
            "address" : "435 Maker Sail Circle",
            "city" : "Atlanta",
            "state" : "GA",
            "zip" : "30022",
            "ssn" : "XXX-XX-XXXX",
            "phone" : {
                "home" : "555-555-5555",
                "work" : "666-666-6666",
                "cell" : "777-777-7777"
            },
            "dob" : {
                "month" : 12,
                "date" : 18,
                "year" : 1979
            }
        },
        "company" : {
            "name" : "Sapient",
            "address" : {
                "address1" : "",
                "city" : "",
                "state" : "",
                "zip" : ""
            }
        },
        "name" : "United",
        "address" : {
            "address1" : "",
            "city" : "",
            "state" : "",
            "zip" : "",
            "phone" : "888-888-8888"
        },
        "policyNum" : "123456",
        "groupNum" : "1234",
        "type" : "PMO"
    },
    "medical" : {
        "smoker" : 0,
        "allergies" : [],
        "drugs" : 0,
        "historyOfCancer" : 0,
        "surgeries" : []
    }
},

{
    "_id" : ObjectId("51d823fc4e7eecde4762cb9d"),
    "personal" : {
        "fname" : "Shaun",
        "lname" : "Wallace",
        "emailAddress" : "swallace@sapient.com",
        "address" : "123 Main Street",
        "city" : "Atlanta",
        "zip" : "30339",
        "ssn" : "XXX-XX-XXXX",
        "gender" : "M",
        "maritalStatus" : "Married",
        "phone" : {
            "home" : "555-555-5555",
            "work" : "666-666-6666",
            "cell" : "777-777-7777"
        },
        "dob" : {
            "month" : 12,
            "date" : 18,
            "year" : 1983
        },
        "userGuid" : "1243asdadassaadzscdfi4k34u39iu"
    },
    "system" : {
        "password" : "password",
        "username" : "swal"
    },
    "insurance" : {
        "mainInsured" : {
            "relationTo" : "self",
            "fname" : "Shaun",
            "lname" : "Wallace",
            "emailAddress" : "swallace@sapient.com",
            "address" : "123 Main Street",
            "city" : "Atlanta",
            "zip" : "30339",
            "ssn" : "XXX-XX-XXXX",
            "phone" : {
                "home" : "555-555-5555",
                "work" : "666-666-6666",
                "cell" : "777-777-7777"
            },
            "dob" : {
                "month" : 12,
                "date" : 18,
                "year" : 1983
            }
        },
        "company" : {
            "name" : "Sapient",
            "address" : {
                "address1" : "",
                "city" : "",
                "state" : "",
                "zip" : ""
            }
        },
        "name" : "United",
        "address" : {
            "address1" : "",
            "city" : "",
            "state" : "",
            "zip" : "",
            "phone" : "888-888-8888"
        },
        "policyNum" : "123456",
        "groupNum" : "1234",
        "type" : "PMO"
    },
    "medical" : {
        "smoker" : 0,
        "allergies" : [],
        "drugs" : 0,
        "historyOfCancer" : 0,
        "surgeries" : []
    }
},

{
    "_id" : ObjectId("51dc15184e7eecde4762cb9f"),
    "personal" : {
        "fname" : "Su",
        "lname" : "Cox",
        "emailAddress" : "scox@sapient.com",
        "address" : "435 Maker Sail Circle",
        "city" : "Atlanta",
        "zip" : "30022",
        "ssn" : "XXX-XX-XXXX",
        "gender" : "M",
        "maritalStatus" : "Married",
        "phone" : {
            "home" : "555-555-5555",
            "work" : "666-666-6666",
            "cell" : "777-777-7777"
        },
        "dob" : {
            "month" : 12,
            "date" : 18,
            "year" : 1979
        },
        "userGuid" : "12434mkghdjfhkjdwi4k34u39iu"
    },
    "system" : {
        "password" : "password",
        "username" : "scox"
    },
    "insurance" : {
        "mainInsured" : {
            "relationTo" : "self",
            "fname" : "Jon",
            "lname" : "Mittelbronn",
            "emailAddress" : "jmittelbronn@sapient.com",
            "address" : "435 Maker Sail Circle",
            "city" : "Atlanta",
            "state" : "GA",
            "zip" : "30022",
            "ssn" : "XXX-XX-XXXX",
            "phone" : {
                "home" : "555-555-5555",
                "work" : "666-666-6666",
                "cell" : "777-777-7777"
            },
            "dob" : {
                "month" : 12,
                "date" : 18,
                "year" : 1979
            }
        },
        "company" : {
            "name" : "Sapient",
            "address" : {
                "address1" : "",
                "city" : "",
                "state" : "",
                "zip" : ""
            }
        },
        "name" : "United",
        "address" : {
            "address1" : "",
            "city" : "",
            "state" : "",
            "zip" : "",
            "phone" : "888-888-8888"
        },
        "policyNum" : "123456",
        "groupNum" : "1234",
        "type" : "PMO"
    },
    "medical" : {
        "smoker" : 0,
        "allergies" : [],
        "drugs" : 0,
        "historyOfCancer" : 0,
        "surgeries" : []
    }
},

{
    "_id" : ObjectId("51dc15354e7eecde4762cba0"),
    "personal" : {
        "fname" : "Tamara",
        "lname" : "Orgias",
        "emailAddress" : "torgias@sapient.com",
        "address" : "435 Maker Sail Circle",
        "city" : "Atlanta",
        "zip" : "30022",
        "ssn" : "XXX-XX-XXXX",
        "gender" : "M",
        "maritalStatus" : "Married",
        "phone" : {
            "home" : "555-555-5555",
            "work" : "666-666-6666",
            "cell" : "777-777-7777"
        },
        "dob" : {
            "month" : 12,
            "date" : 18,
            "year" : 1979
        },
        "userGuid" : "12434mjsdasdavmbk4k34u39iu"
    },
    "system" : {
        "password" : "password",
        "username" : "torg"
    },
    "insurance" : {
        "mainInsured" : {
            "relationTo" : "self",
            "fname" : "Jon",
            "lname" : "Mittelbronn",
            "emailAddress" : "jmittelbronn@sapient.com",
            "address" : "435 Maker Sail Circle",
            "city" : "Atlanta",
            "state" : "GA",
            "zip" : "30022",
            "ssn" : "XXX-XX-XXXX",
            "phone" : {
                "home" : "555-555-5555",
                "work" : "666-666-6666",
                "cell" : "777-777-7777"
            },
            "dob" : {
                "month" : 12,
                "date" : 18,
                "year" : 1979
            }
        },
        "company" : {
            "name" : "Sapient",
            "address" : {
                "address1" : "",
                "city" : "",
                "state" : "",
                "zip" : ""
            }
        },
        "name" : "United",
        "address" : {
            "address1" : "",
            "city" : "",
            "state" : "",
            "zip" : "",
            "phone" : "888-888-8888"
        },
        "policyNum" : "123456",
        "groupNum" : "1234",
        "type" : "PMO"
    },
    "medical" : {
        "smoker" : 0,
        "allergies" : [],
        "drugs" : 0,
        "historyOfCancer" : 0,
        "surgeries" : []
    }
},

{
    "_id" : ObjectId("51dc16b14e7eecde4762cba1"),
    "personal" : {
        "fname" : "Hadi",
        "lname" : "Seyfi",
        "emailAddress" : "hseyfi@sapient.com",
        "address" : "435 Maker Sail Circle",
        "city" : "Atlanta",
        "zip" : "30022",
        "ssn" : "XXX-XX-XXXX",
        "gender" : "M",
        "maritalStatus" : "Married",
        "phone" : {
            "home" : "555-555-5555",
            "work" : "666-666-6666",
            "cell" : "777-777-7777"
        },
        "dob" : {
            "month" : 12,
            "date" : 18,
            "year" : 1979
        },
        "userGuid" : "12434mj879236kj39iu"
    },
    "system" : {
        "password" : "password",
        "username" : "hsey"
    },
    "insurance" : {
        "mainInsured" : {
            "relationTo" : "self",
            "fname" : "Jon",
            "lname" : "Mittelbronn",
            "emailAddress" : "jmittelbronn@sapient.com",
            "address" : "435 Maker Sail Circle",
            "city" : "Atlanta",
            "state" : "GA",
            "zip" : "30022",
            "ssn" : "XXX-XX-XXXX",
            "phone" : {
                "home" : "555-555-5555",
                "work" : "666-666-6666",
                "cell" : "777-777-7777"
            },
            "dob" : {
                "month" : 12,
                "date" : 18,
                "year" : 1979
            }
        },
        "company" : {
            "name" : "Sapient",
            "address" : {
                "address1" : "",
                "city" : "",
                "state" : "",
                "zip" : ""
            }
        },
        "name" : "United",
        "address" : {
            "address1" : "",
            "city" : "",
            "state" : "",
            "zip" : "",
            "phone" : "888-888-8888"
        },
        "policyNum" : "123456",
        "groupNum" : "1234",
        "type" : "PMO"
    },
    "medical" : {
        "smoker" : 0,
        "allergies" : [],
        "drugs" : 0,
        "historyOfCancer" : 0,
        "surgeries" : []
    }
}]